Metadata-Version: 2.1
Name: blastpy3
Version: 0.3.0
Summary: Lightweight High level Python 3 API for NCBI BLAST
Home-page: https://github.com/a-slide/blastpy
Author: Adrien Leger
Author-email: aleg@ebi.ac.uk
License: GPLv3
Platform: UNKNOWN
Classifier: Development Status :: 3 - Alpha
Classifier: Intended Audience :: Science/Research
Classifier: Topic :: Scientific/Engineering :: Bio-Informatics
Classifier: License :: OSI Approved :: GNU General Public License v3 (GPLv3)
Classifier: Programming Language :: Python :: 3
Requires-Python: >=3.5
